nti/__init__.py
nti/zope_catalog/__init__.py
nti/zope_catalog/catalog.py
nti/zope_catalog/configure.zcml
nti/zope_catalog/datetime.py
nti/zope_catalog/index.py
nti/zope_catalog/interfaces.py
nti/zope_catalog/mixin.py
nti/zope_catalog/number.py
nti/zope_catalog/string.py
nti/zope_catalog/topic.py
nti/zope_catalog/tests/__init__.py
nti/zope_catalog/tests/test_catalog.py
nti/zope_catalog/tests/test_datetime.py
nti/zope_catalog/tests/test_index.py
nti/zope_catalog/tests/test_number.py
nti/zope_catalog/tests/test_string.py
nti/zope_catalog/tests/test_topic.py
nti.zope_catalog-4.1.0.dist-info/AUTHORS
nti.zope_catalog-4.1.0.dist-info/LICENSE
nti.zope_catalog-4.1.0.dist-info/METADATA
nti.zope_catalog-4.1.0.dist-info/WHEEL
nti.zope_catalog-4.1.0.dist-info/top_level.txt
nti.zope_catalog-4.1.0.dist-info/zip-safe
nti.zope_catalog-4.1.0.dist-info/RECORD
