Metadata-Version: 2.1
Name: nti.zope_catalog
Version: 4.1.0
Summary: NTI Zope Catalog
Home-page: https://github.com/OpenNTI/nti.zope_catalog
Author: Jason Madden
Author-email: jason@nextthought.com
License: Apache
Project-URL: Documentation, https://ntizope-catalog.readthedocs.io/en/latest/
Keywords: Zope Catalog
Classifier: Intended Audience :: Developers
Classifier: Natural Language :: English
Classifier: Operating System :: OS Independent
Classifier: Framework :: ZODB
Classifier: License :: OSI Approved :: Apache Software License
Classifier: Programming Language :: Python :: 3
Classifier: Programming Language :: Python :: 3 :: Only
Classifier: Programming Language :: Python :: 3.10
Classifier: Programming Language :: Python :: 3.11
Classifier: Programming Language :: Python :: 3.12
Classifier: Programming Language :: Python :: 3.13
Classifier: Programming Language :: Python :: Implementation :: CPython
Classifier: Programming Language :: Python :: Implementation :: PyPy
Requires-Python: >=3.10
License-File: LICENSE
License-File: AUTHORS
Requires-Dist: BTrees>=4.8.0
Requires-Dist: nti.property>=1.0.0
Requires-Dist: nti.zodb>=1.0.0
Requires-Dist: persistent
Requires-Dist: pytz
Requires-Dist: six
Requires-Dist: zc.catalog>=2.0.1
Requires-Dist: ZODB>=5.0.0
Requires-Dist: zope.cachedescriptors
Requires-Dist: zope.catalog
Requires-Dist: zope.component
Requires-Dist: zope.container
Requires-Dist: zope.index
Requires-Dist: zope.interface
Requires-Dist: zope.location
Provides-Extra: docs
Requires-Dist: Sphinx; extra == "docs"
Requires-Dist: repoze.sphinx.autointerface; extra == "docs"
Requires-Dist: sphinx-rtd-theme; extra == "docs"
Provides-Extra: test
Requires-Dist: pyhamcrest; extra == "test"
Requires-Dist: nti.testing; extra == "test"
Requires-Dist: zope.testing; extra == "test"
Requires-Dist: zope.testrunner; extra == "test"
